Workbook

Sheet Tiering Methodology
A1: Tiering Methodology
A3: Rate each factor from 1 (lowest inherent risk) to 5 (highest inherent risk).
A5: Risk Factor | B5: Weight | C5: What It Measures | D5: Rating Guidance | F5: Tier | G5: Risk Score | H5: Expected Treatment
A6: Business Criticality | B6: 0.25 | C6: Impact if the vendor service fails or is unavailable. | D6: 1 = minimal impact; 5 = severe operational disruption or mission-critical service. | F6: Tier 1 | G6: 75–100 or automatic trigger | H6: Enhanced due diligence, evidence validation, executive visibility, annual or more frequent reassessment.
A7: Data Sensitivity | B7: 0.2 | C7: Sensitivity of information processed, stored, transmitted, or accessed. | D7: 1 = public data; 5 = highly restricted personal, financial, health, or proprietary data. | F7: Tier 2 | G7: 45–74.99 | H7: Standard security assessment, contract review, risk-based evidence, reassessment every 2 years.
A8: System Access | B8: 0.2 | C8: Level of logical, network, application, API, or physical access. | D8: 1 = no access; 5 = privileged, administrative, persistent, or broad production access. | F8: Tier 3 | G8: Below 45 | H8: Basic screening, standard contractual protections, reassessment every 3 years.
A9: Regulatory Exposure | B9: 0.15 | C9: Potential legal, privacy, contractual, or regulatory impact. | D9: 1 = little exposure; 5 = direct exposure to major regulated obligations.
A10: Fourth-Party Dependency | B10: 0.1 | C10: Reliance on subcontractors, sub-processors, cloud providers, or other external parties. | D10: 1 = limited reliance; 5 = heavy or opaque concentration on critical fourth parties. | F10: Automatic Tier 1 Triggers
A11: Availability Requirements | B11: 0.1 | C11: Required uptime, recovery speed, and tolerance for service interruption. | D11: 1 = interruption tolerated; 5 = near-continuous availability required. | F11: Trigger | G11: Rule | H11: Rationale
A12: Total Weight | B12: =SUM(B6:B11) -> 1 | F12: Critical availability dependency | G12: Business Criticality = 5 AND Availability = 5 | H12: A severe outage could materially interrupt operations.
F13: Restricted data with powerful access | G13: Data Sensitivity = 5 AND System Access ≥ 4 | H13: Combines crown-jewel information with elevated access.
A14: Scoring Formula | F14: Maximum regulatory exposure | G14: Regulatory Exposure = 5 | H14: Failure could create major legal, privacy, or regulatory impact.
A15: Weighted Score = Σ (Factor Rating × Factor Weight). Risk Percentage = Weighted Score ÷ 5 × 100. Final Tier may be raised through a documented manual override but should not be lowered without approval.

Sheet Lists
A1: Rating | B1: Department | C1: Vendor Type | D1: Access Level | E1: Status | F1: Tier Override | G1: Yes/No | H1: Regulatory Scope
A2: 1 | B2: IT | C2: Cloud / SaaS | D2: None | E2: Planned | G2: Yes | H2: None
A3: 2 | B3: Security | C3: Professional Services | D3: User | E3: Onboarding | F3: Tier 1 | G3: No | H3: Privacy
A4: 3 | B4: Finance | C4: Business Process Outsourcing | D4: Elevated | E4: Active | F4: Tier 2 | H4: Financial
A5: 4 | B5: HR | C5: Legal | D5: Privileged | E5: Under Review | F5: Tier 3 | H5: Healthcare
A6: 5 | B6: Legal | C6: Marketing | D6: API / Service Account | E6: Remediation | H6: Payment Card
B7: Procurement | C7: Facilities / Office | D7: Network | E7: Offboarding | H7: Multiple
B8: Operations | C8: Data / Analytics | D8: Physical | E8: Terminated
B9: Marketing | C9: Payroll / HR
B10: Other | C10: Other

Sheet Vendor Inventory
A1: Vendor Inventory
A3: Enter one supplier per row. Vendor IDs are preassigned for up to 20 third parties.
A4: Vendor ID | B4: Vendor Name | C4: Service / Product | D4: Vendor Type | E4: Business Owner | F4: Department | G4: Lifecycle Status | H4: Contract Start | I4: Contract End | J4: Primary Geography | K4: Data Types Handled | L4: Connected Systems | M4: Access Level | N4: Regulatory Scope | O4: Critical Service? | P4: Fourth Parties Known? | Q4: Notes
A5: V-001 | B5: NorthGrid Cloud Services | C5: Cloud hosting | D5: Cloud / SaaS | E5: Director of IT Infrastructure | F5: IT | G5: Active | H5: 45658 | I5: 46752 | J5: United States | K5: Customer records, employee records, application data, system configurations, backups, IP addresses, authentication logs, and administrator information | L5: WallGate cloud-hosted applications, identity provider, backup platform, monitoring tools, and administrator console | M5: Privileged | N5: Privacy | O5: Yes | P5: Yes | Q5: Critical cloud-hosting provider with privileged administrative access. Annual review should validate data-residency locations, backup recovery testing, administrator access controls, and fourth-party hosting dependencies.
A6: V-002 | B6: ClearPay Workforce Solutions | C6: Payroll | D6: Payroll / HR | E6: Payroll Manager or HR Director | F6: HR | G6: Active | H6: 45658 | I6: 46387 | J6: United States | K6: Employee names, addresses, Social Security numbers, bank-account details, salary information, tax records, and benefits information | L6: HR information system, employee timekeeping system, finance system, banking file-transfer portal, and SSO | M6: API / Service Account | N6: Multiple | O6: Yes | P6: Yes | Q6: Processes highly sensitive employee payroll and banking information through automated integrations. Access should be limited to approved service accounts, and annual reviews should confirm encryption, payroll-file security, and subcontractor oversight.
A7: V-003 | B7: VenueBridge Tickets | C7: Ticketing | D7: Cloud / SaaS | E7: Director of Ticketing Operations | F7: Operations | G7: Under Review | H7: 45170 | I7: 46265 | J7: United States / Ireland | K7: Attendee names, email addresses, phone numbers, ticket details, purchase history, payment tokens, and event attendance records | L7: WallGate website, customer relationship management system, payment gateway, event-management platform, and CrowdFlow access system | M7: API / Service Account | N7: Multiple | O7: Yes | P7: Yes | Q7: Contract is under review before expiration. Renewal should require current security evidence, availability testing, payment-data responsibilities, incident-notification terms, and confirmation of all cloud and payment-related fourth parties.
A8: V-004 | B8: Harrison, Cole & Mercer LLP | C8: Law firm | D8: Legal | E8: General Counsel | F8: Legal | G8: Active | H8: 46023 | I8: 46387 | J8: United States | K8: Contracts, employee-relations records, litigation documents, incident records, privileged communications, and business-confidential information | L8: Microsoft 365 email, SharePoint legal repository, secure file-transfer portal, and HR case-management system | M8: User | N8: Privacy | O8: No | P8: Yes | Q8: Handles legally privileged and business-confidential information. Documents should be exchanged through approved secure channels, and access to HR or legal repositories should follow least-privilege requirements.
A9: V-005 | B9: Brightline Creative Group | C9: Marketing | D9: Marketing | E9: Marketing Director | F9: Marketing | G9: Active | H9: 46113 | I9: 46477 | J9: United States / United Kingdom | K9: Customer email addresses, marketing preferences, campaign analytics, social-media information, photographs, and brand assets | L9: Website content-management system, customer relationship management system, email-marketing platform, social-media accounts, and analytics platform | M9: User | N9: Privacy | O9: No | P9: Yes | Q9: Access is limited to approved marketing, website, and social-media accounts. WallGate should require individual accounts, MFA, prompt access removal, and restrictions on sharing customer data with advertising or analytics partners.
A10: V-006 | B10: MetroDesk Office Supply | C10: Office supplies | D10: Facilities / Office | E10: Procurement Manager | F10: Procurement | G10: Active | H10: 46023 | I10: 46387 | J10: United States | K10: Business contact information, shipping addresses, purchase orders, invoices, and payment information | L10: Procurement portal, accounts-payable system, and invoice-processing system | M10: None | N10: None | O10: No | P10: Yes | Q10: No direct access to WallGate production systems. Fourth parties are limited to product distributors and delivery carriers.
A11: V-007 | B11: SentinelPeak Security | C11: Managed security monitoring and incident response | D11: Professional Services | E11: Chief Information Security Officer | F11: Security | G11: Onboarding | H11: 46235 | I11: 46965 | J11: United States / Canada | K11: Security alerts, log data, IP addresses, usernames, device information, incident records, vulnerability information, and administrator information | L11: SIEM, EDR platform, firewalls, identity provider, cloud logs, vulnerability-management platform, and incident-ticketing system | M11: Privileged | N11: Privacy | O11: Yes | P11: Yes | Q11: Vendor is onboarding. Privileged access will not be enabled until security evidence, MFA, access logging, and incident-response procedures are approved.
A12: V-008 | B12: CrowdFlow Access Systems | C12: Digital ticket scanning and venue access control | D12: Cloud / SaaS | E12: Venue Operations Manager | F12: Operations | G12: Under Review | H12: 45566 | I12: 46295 | J12: United States / Russia | K12: Attendee names, email addresses, ticket identifiers, access records, device logs, and administrator information | L12: VenueBridge ticketing platform, ticket scanners, access-control devices, event-management system, and identity provider | M12: Privileged | N12: Privacy | O12: Yes | P12: Yes | Q12: U.S.-based vendor relies on VolgaTech Support LLC, a Russia-based software-development and technical-support subcontractor. Contract renewal is pending sanctions screening, ownership validation, banking review, privileged-access assessment, and approval of a geographic exit plan.
A13: V-009 | B13: HarborPoint Payment Solutions | C13: Credit-card payment processing | D13: Business Process Outsourcing | E13: Finance Director or Controller | F13: Finance | G13: Remediation | H13: 46023 | I13: 46387 | J13: United States / India | K13: Cardholder names, payment-card information, transaction records, billing addresses, payment tokens, and fraud-monitoring data | L13: Ticketing platform, point-of-sale terminals, finance system, payment gateway, and fraud-monitoring system | M13: API / Service Account | N13: Payment Card | O13: Yes | P13: Yes | Q13: Vendor is in remediation. Long-term renewal is pending an updated PCI DSS attestation, incident-notification requirements, and closure of identified payment-security findings.
A14: V-010 | B14: StageLink Production Services | C14: Audio, lighting, and stage-production equipment | D14: Professional Services | E14: Director of Event Production | F14: Operations | G14: Active | H14: 46082 | I14: 46387 | J14: United States | K14: Event schedules, venue layouts, employee and contractor contact information, equipment inventories, and production plans | L14: Event-production scheduling system, equipment inventory system, and venue network for approved production devices | M14: Network | N14: None | O14: Yes | P14: Yes | Q14: Production equipment may connect only to an isolated event network. Temporary accounts and network access must be removed after each event.
A15: V-011 | B15: IronGate Facility Management | C15: Venue maintenance, cleaning, and repairs | D15: Facilities / Office | E15: Facilities Manager | F15: Operations | G15: Active | H15: 46023 | I15: 46387 | J15: United States | K15: Employee and contractor contact information, facility access records, maintenance records, floor plans, and work orders | L15: Facilities-management system, work-order platform, building-access system, and maintenance-record repository | M15: Physical | N15: None | O15: Yes | P15: Yes | Q15: Physical access is limited to approved maintenance areas. Entry into server rooms or other restricted spaces requires authorization and escort.
A16: V-012 | B16: SafeGuard Event Staffing | C16: Security guards and crowd-management staff | D16: Business Process Outsourcing | E16: Director of Venue Security | F16: Security | G16: Active | H16: 46023 | I16: 46387 | J16: United States | K16: Guard and contractor names, contact information, schedules, licensing information, incident reports, and venue-access records | L16: Staff-scheduling system, visitor-management platform, access-control system, and incident-reporting system | M16: Physical | N16: Privacy | O16: Yes | P16: Yes | Q16: Vendor must verify guard licenses and background checks. Subcontracted guards require WallGate approval before assignment.
... A20: V-016 | B20: DataPulse Analytics | C20: Customer, ticket-sales, and event-performance analytics | D20: Data / Analytics | E20: Marketing Analytics Manager | F20: Marketing | G20: Remediation | H20: 45748 | I20: 46477 | J20: United States / Ireland | K20: Customer identifiers, ticket-purchase history, attendance records, campaign interactions, demographic data, device information, and aggregated analytics | L20: Data warehouse, ticketing platform, customer relationship management system, marketing automation platform, and website analytics | M20: API / Service Account | N20: Privacy | O20: No | P20: Yes | Q20: Vendor is in remediation. Renewal is pending evidence of data minimization, retention limits, deletion procedures, and restrictions on fourth-party data sharing.
A21: V-017
A22: V-018
A23: V-019
A24: V-020

Sheet Risk Assessment
A1: Inherent-Risk Assessment
A3: Select a 1–5 rating for each risk factor. Complete all six ratings to calculate the score.
A4: Vendor ID | B4: Vendor Name | C4: Business Criticality 25% | D4: Data Sensitivity 20% | E4: System Access 20% | F4: Regulatory Exposure 15% | G4: Fourth-Party Dependency 10% | H4: Availability Requirements 10% | I4: Weighted Score (1–5) | J4: Risk % | K4: Auto Tier 1 Trigger | L4: Assessment Notes
A5: V-001 | B5: =IF('Vendor Inventory'!B5="","",'Vendor Inventory'!B5) -> NorthGrid Cloud Services | C5: 5 | D5: 5 | E5: 5 | F5: 4 | G5: 4 | H5: 5 | I5: =IF(COUNT(C5:H5)<6,"",C5*'Tiering Methodology'!$B$6+D5*'Tiering Methodology'!$B$7+E5*'Tiering Methodology'!$B$8+F5*'Tiering Methodology'!$B$9+G5*'Tiering Methodology'!$B$10+H5*'Tiering Methodology'!$B$11) -> 4.75 | J5: =IF(I5="","",I5/5*100) -> 95 | K5: =IF(COUNT(C5:H5)<6,"",IF(OR(AND(C5=5,H5=5),AND(D5=5,E5>=4),F5=5),"Yes","No")) -> Yes | L5: Mission-critical cloud hosting, highly sensitive customer and employee data, privileged administrative access, and near-continuous availability requirements. Assessment should prioritize administrator controls, backup recovery, data residency, and critical fourth-party dependencies.
A6: V-002 | B6: =IF('Vendor Inventory'!B6="","",'Vendor Inventory'!B6) -> ClearPay Workforce Solutions | C6: 4 | D6: 5 | E6: 4 | F6: 5 | G6: 4 | H6: 4 | I6: =IF(COUNT(C6:H6)<6,"",C6*'Tiering Methodology'!$B$6+D6*'Tiering Methodology'!$B$7+E6*'Tiering Methodology'!$B$8+F6*'Tiering Methodology'!$B$9+G6*'Tiering Methodology'!$B$10+H6*'Tiering Methodology'!$B$11) -> 4.35 | J6: =IF(I6="","",I6/5*100) -> 87 | K6: =IF(COUNT(C6:H6)<6,"",IF(OR(AND(C6=5,H6=5),AND(D6=5,E6>=4),F6=5),"Yes","No")) -> Yes | L6: Highly sensitive payroll, banking, tax, and employee data; automated system integrations; and significant regulatory exposure. Review should validate encryption, service-account security, payroll continuity, and oversight of banking and tax-processing fourth parties.
A7: V-003 | B7: =IF('Vendor Inventory'!B7="","",'Vendor Inventory'!B7) -> VenueBridge Tickets | C7: 5 | D7: 4 | E7: 4 | F7: 4 | G7: 4 | H7: 5 | I7: =IF(COUNT(C7:H7)<6,"",C7*'Tiering Methodology'!$B$6+D7*'Tiering Methodology'!$B$7+E7*'Tiering Methodology'!$B$8+F7*'Tiering Methodology'!$B$9+G7*'Tiering Methodology'!$B$10+H7*'Tiering Methodology'!$B$11) -> 4.35 | J7: =IF(I7="","",I7/5*100) -> 87 | K7: =IF(COUNT(C7:H7)<6,"",IF(OR(AND(C7=5,H7=5),AND(D7=5,E7>=4),F7=5),"Yes","No")) -> Yes | L7: Ticket sales, customer entry, and event revenue depend on the platform. The vendor processes customer and payment-related data through multiple integrations and requires high availability; renewal should include resilience evidence, incident-notification terms, and fourth-party transparency.
A8: V-004 | B8: =IF('Vendor Inventory'!B8="","",'Vendor Inventory'!B8) -> Harrison, Cole & Mercer LLP | C8: 3 | D8: 5 | E8: 2 | F8: 4 | G8: 3 | H8: 2 | I8: =IF(COUNT(C8:H8)<6,"",C8*'Tiering Methodology'!$B$6+D8*'Tiering Methodology'!$B$7+E8*'Tiering Methodology'!$B$8+F8*'Tiering Methodology'!$B$9+G8*'Tiering Methodology'!$B$10+H8*'Tiering Methodology'!$B$11) -> 3.25 | J8: =IF(I8="","",I8/5*100) -> 65 | K8: =IF(COUNT(C8:H8)<6,"",IF(OR(AND(C8=5,H8=5),AND(D8=5,E8>=4),F8=5),"Yes","No")) -> No | L8: Highly sensitive legal, employment, litigation, and privileged information. Risk is reduced by limited user-level access and lower availability requirements; assessment should focus on secure document transfer, least privilege, retention, and e-discovery subcontractors.
A9: V-005 | B9: =IF('Vendor Inventory'!B9="","",'Vendor Inventory'!B9) -> Brightline Creative Group | C9: 2 | D9: 3 | E9: 2 | F9: 3 | G9: 4 | H9: 2 | I9: =IF(COUNT(C9:H9)<6,"",C9*'Tiering Methodology'!$B$6+D9*'Tiering Methodology'!$B$7+E9*'Tiering Methodology'!$B$8+F9*'Tiering Methodology'!$B$9+G9*'Tiering Methodology'!$B$10+H9*'Tiering Methodology'!$B$11) -> 2.55 | J9: =IF(I9="","",I9/5*100) -> 51 | K9: =IF(COUNT(C9:H9)<6,"",IF(OR(AND(C9=5,H9=5),AND(D9=5,E9>=4),F9=5),"Yes","No")) -> No | L9: Customer marketing data, access to website and social-media accounts, and heavy reliance on advertising and analytics partners. Review should confirm MFA, individual accounts, customer-consent practices, and restrictions on data sharing.
A10: V-006 | B10: =IF('Vendor Inventory'!B10="","",'Vendor Inventory'!B10) -> MetroDesk Office Supply | C10: 1 | D10: 2 | E10: 1 | F10: 1 | G10: 3 | H10: 1 | I10: =IF(COUNT(C10:H10)<6,"",C10*'Tiering Methodology'!$B$6+D10*'Tiering Methodology'!$B$7+E10*'Tiering Methodology'!$B$8+F10*'Tiering Methodology'!$B$9+G10*'Tiering Methodology'!$B$10+H10*'Tiering Methodology'!$B$11) -> 1.4 | J10: =IF(I10="","",I10/5*100) -> 28 | K10: =IF(COUNT(C10:H10)<6,"",IF(OR(AND(C10=5,H10=5),AND(D10=5,E10>=4),F10=5),"Yes","No")) -> No | L10: Easily replaceable, handles routine business information, and has no direct access to WallGate production systems. Basic screening and confirmation of delivery and distributor fourth parties are sufficient.
A11: V-007 | B11: =IF('Vendor Inventory'!B11="","",'Vendor Inventory'!B11) -> SentinelPeak Security | C11: 5 | D11: 4 | E11: 5 | F11: 4 | G11: 4 | H11: 5 | I11: =IF(COUNT(C11:H11)<6,"",C11*'Tiering Methodology'!$B$6+D11*'Tiering Methodology'!$B$7+E11*'Tiering Methodology'!$B$8+F11*'Tiering Methodology'!$B$9+G11*'Tiering Methodology'!$B$10+H11*'Tiering Methodology'!$B$11) -> 4.55 | J11: =IF(I11="","",I11/5*100) -> 91 | K11: =IF(COUNT(C11:H11)<6,"",IF(OR(AND(C11=5,H11=5),AND(D11=5,E11>=4),F11=5),"Yes","No")) -> Yes | L11: Critical security-monitoring role, privileged access to core security systems, sensitive log and incident data, and 24/7 availability requirements. Onboarding should require MFA, PAM, access logging, incident-response procedures, and continuity evidence.
A12: V-008 | B12: =IF('Vendor Inventory'!B12="","",'Vendor Inventory'!B12) -> CrowdFlow Access Systems | C12: 5 | D12: 4 | E12: 4 | F12: 4 | G12: 5 | H12: 5 | I12: =IF(COUNT(C12:H12)<6,"",C12*'Tiering Methodology'!$B$6+D12*'Tiering Methodology'!$B$7+E12*'Tiering Methodology'!$B$8+F12*'Tiering Methodology'!$B$9+G12*'Tiering Methodology'!$B$10+H12*'Tiering Methodology'!$B$11) -> 4.45 | J12: =IF(I12="","",I12/5*100) -> 89 | K12: =IF(COUNT(C12:H12)<6,"",IF(OR(AND(C12=5,H12=5),AND(D12=5,E12>=4),F12=5),"Yes","No")) -> Yes | L12: Mission-critical venue access, sensitive attendee information, privileged platform access, high availability requirements, and significant reliance on a Russia-based fourth party. Renewal requires sanctions screening, ownership validation, privileged-access review, continuity testing, and an approved geographic exit plan.
A13: V-009 | B13: =IF('Vendor Inventory'!B13="","",'Vendor Inventory'!B13) -> HarborPoint Payment Solutions | C13: 5 | D13: 5 | E13: 4 | F13: 5 | G13: 5 | H13: 5 | I13: =IF(COUNT(C13:H13)<6,"",C13*'Tiering Methodology'!$B$6+D13*'Tiering Methodology'!$B$7+E13*'Tiering Methodology'!$B$8+F13*'Tiering Methodology'!$B$9+G13*'Tiering Methodology'!$B$10+H13*'Tiering Methodology'!$B$11) -> 4.8 | J13: =IF(I13="","",I13/5*100) -> 96 | K13: =IF(COUNT(C13:H13)<6,"",IF(OR(AND(C13=5,H13=5),AND(D13=5,E13>=4),F13=5),"Yes","No")) -> Yes | L13: Payment processing directly supports WallGate revenue and involves payment-card data, API integrations, major regulatory exposure, and numerous financial fourth parties. Vendor remains in remediation pending current PCI DSS evidence, stronger incident-notification terms, and closure of payment-security findings.
A14: V-010 | B14: =IF('Vendor Inventory'!B14="","",'Vendor Inventory'!B14) -> StageLink Production Services | C14: 4 | D14: 2 | E14: 3 | F14: 2 | G14: 4 | H14: 4 | I14: =IF(COUNT(C14:H14)<6,"",C14*'Tiering Methodology'!$B$6+D14*'Tiering Methodology'!$B$7+E14*'Tiering Methodology'!$B$8+F14*'Tiering Methodology'!$B$9+G14*'Tiering Methodology'!$B$10+H14*'Tiering Methodology'!$B$11) -> 3.1 | J14: =IF(I14="","",I14/5*100) -> 62 | K14: =IF(COUNT(C14:H14)<6,"",IF(OR(AND(C14=5,H14=5),AND(D14=5,E14>=4),F14=5),"Yes","No")) -> No | L14: Audio, lighting, and production services are highly important during live events and may connect equipment to venue networks. Risk is limited by low data sensitivity; controls should include network isolation, temporary access, and removal of vendor devices and accounts after events.
A15: V-011 | B15: =IF('Vendor Inventory'!B15="","",'Vendor Inventory'!B15) -> IronGate Facility Management | C15: 4 | D15: 2 | E15: 3 | F15: 3 | G15: 4 | H15: 4 | I15: =IF(COUNT(C15:H15)<6,"",C15*'Tiering Methodology'!$B$6+D15*'Tiering Methodology'!$B$7+E15*'Tiering Methodology'!$B$8+F15*'Tiering Methodology'!$B$9+G15*'Tiering Methodology'!$B$10+H15*'Tiering Methodology'!$B$11) -> 3.25 | J15: =IF(I15="","",I15/5*100) -> 65 | K15: =IF(COUNT(C15:H15)<6,"",IF(OR(AND(C15=5,H15=5),AND(D15=5,E15>=4),F15=5),"Yes","No")) -> No | L15: Vendor’s role in maintaining safe and operational facilities, physical access to venue areas, and reliance on specialty subcontractors. Assessment should confirm access restrictions, escort requirements, safety compliance, and approval of subcontracted technicians.
A16: V-012 | B16: =IF('Vendor Inventory'!B16="","",'Vendor Inventory'!B16) -> SafeGuard Event Staffing | C16: 5 | D16: 3 | E16: 3 | F16: 4 | G16: 4 | H16: 5 | I16: =IF(COUNT(C16:H16)<6,"",C16*'Tiering Methodology'!$B$6+D16*'Tiering Methodology'!$B$7+E16*'Tiering Methodology'!$B$8+F16*'Tiering Methodology'!$B$9+G16*'Tiering Methodology'!$B$10+H16*'Tiering Methodology'!$B$11) -> 3.95 | J16: =IF(I16="","",I16/5*100) -> 79 | K16: =IF(COUNT(C16:H16)<6,"",IF(OR(AND(C16=5,H16=5),AND(D16=5,E16>=4),F16=5),"Yes","No")) -> Yes | L16: Security staffing and crowd management are essential for attendee safety and event operations. The vendor has physical access, handles incident and licensing information, and may use subcontracted guards; review should validate licenses, background checks, staffing continuity, and subcontractor approval.
... A20: V-016 | B20: =IF('Vendor Inventory'!B20="","",'Vendor Inventory'!B20) -> DataPulse Analytics | C20: 3 | D20: 4 | E20: 4 | F20: 4 | G20: 4 | H20: 2 | I20: =IF(COUNT(C20:H20)<6,"",C20*'Tiering Methodology'!$B$6+D20*'Tiering Methodology'!$B$7+E20*'Tiering Methodology'!$B$8+F20*'Tiering Methodology'!$B$9+G20*'Tiering Methodology'!$B$10+H20*'Tiering Methodology'!$B$11) -> 3.55 | J20: =IF(I20="","",I20/5*100) -> 71 | K20: =IF(COUNT(C20:H20)<6,"",IF(OR(AND(C20=5,H20=5),AND(D20=5,E20>=4),F20=5),"Yes","No")) -> No | L20: Automated access to customer, ticketing, CRM, and behavioral analytics data. Although the service is not required for live-event continuity, remediation should address data minimization, retention limits, deletion procedures, consent, and restrictions on fourth-party data sharing.
A21: V-017 | B21: =IF('Vendor Inventory'!B21="","",'Vendor Inventory'!B21) | I21: =IF(COUNT(C21:H21)<6,"",C21*'Tiering Methodology'!$B$6+D21*'Tiering Methodology'!$B$7+E21*'Tiering Methodology'!$B$8+F21*'Tiering Methodology'!$B$9+G21*'Tiering Methodology'!$B$10+H21*'Tiering Methodology'!$B$11) | J21: =IF(I21="","",I21/5*100) | K21: =IF(COUNT(C21:H21)<6,"",IF(OR(AND(C21=5,H21=5),AND(D21=5,E21>=4),F21=5),"Yes","No"))
A22: V-018 | B22: =IF('Vendor Inventory'!B22="","",'Vendor Inventory'!B22) | I22: =IF(COUNT(C22:H22)<6,"",C22*'Tiering Methodology'!$B$6+D22*'Tiering Methodology'!$B$7+E22*'Tiering Methodology'!$B$8+F22*'Tiering Methodology'!$B$9+G22*'Tiering Methodology'!$B$10+H22*'Tiering Methodology'!$B$11) | J22: =IF(I22="","",I22/5*100) | K22: =IF(COUNT(C22:H22)<6,"",IF(OR(AND(C22=5,H22=5),AND(D22=5,E22>=4),F22=5),"Yes","No"))
A23: V-019 | B23: =IF('Vendor Inventory'!B23="","",'Vendor Inventory'!B23) | I23: =IF(COUNT(C23:H23)<6,"",C23*'Tiering Methodology'!$B$6+D23*'Tiering Methodology'!$B$7+E23*'Tiering Methodology'!$B$8+F23*'Tiering Methodology'!$B$9+G23*'Tiering Methodology'!$B$10+H23*'Tiering Methodology'!$B$11) | J23: =IF(I23="","",I23/5*100) | K23: =IF(COUNT(C23:H23)<6,"",IF(OR(AND(C23=5,H23=5),AND(D23=5,E23>=4),F23=5),"Yes","No"))
A24: V-020 | B24: =IF('Vendor Inventory'!B24="","",'Vendor Inventory'!B24) | I24: =IF(COUNT(C24:H24)<6,"",C24*'Tiering Methodology'!$B$6+D24*'Tiering Methodology'!$B$7+E24*'Tiering Methodology'!$B$8+F24*'Tiering Methodology'!$B$9+G24*'Tiering Methodology'!$B$10+H24*'Tiering Methodology'!$B$11) | J24: =IF(I24="","",I24/5*100) | K24: =IF(COUNT(C24:H24)<6,"",IF(OR(AND(C24=5,H24=5),AND(D24=5,E24>=4),F24=5),"Yes","No"))

Sheet Tiering Results
A1: Vendor Tiering Results
A3: Review the calculated tier, document any approved override, and assign the required assessment approach.
A4: Vendor ID | B4: Vendor Name | C4: Weighted Score | D4: Risk % | E4: Auto Trigger | F4: Calculated Tier | G4: Manual Override | H4: Final Tier | I4: Required Due Diligence | J4: Reassessment Frequency | K4: Business Owner | L4: Review Status | M4: Reviewer Notes
A5: V-001 | B5: =IF('Vendor Inventory'!B5="","",'Vendor Inventory'!B5) -> NorthGrid Cloud Services | C5: ='Risk Assessment'!I5 -> 4.75 | D5: ='Risk Assessment'!J5 -> 95 | E5: =IF('Risk Assessment'!K5="","",'Risk Assessment'!K5) -> Yes | F5: =IF(D5="","",IF(E5="Yes","Tier 1",IF(D5>=75,"Tier 1",IF(D5>=45,"Tier 2","Tier 3")))) -> Tier 1 | H5: =IF(G5<>"",G5,F5) -> Tier 1 | I5: =IF(H5="","",IF(H5="Tier 1","Enhanced assessment + evidence validation",IF(H5="Tier 2","Standard security assessment","Basic screening"))) -> Enhanced assessment + evidence validation | J5: =IF(H5="","",IF(H5="Tier 1","Annual",IF(H5="Tier 2","Every 2 years","Every 3 years"))) -> Annual | K5: =IF('Vendor Inventory'!E5="","",'Vendor Inventory'!E5) -> Director of IT Infrastructure | L5: Complete | M5: Tier 1 classification confirmed due to critical cloud hosting, privileged administrative access, sensitive hosted data, and high availability requirements. Enhanced assessment completed; continue annual review of access controls, data residency, backup recovery, and fourth-party hosting dependencies.
A6: V-002 | B6: =IF('Vendor Inventory'!B6="","",'Vendor Inventory'!B6) -> ClearPay Workforce Solutions | C6: ='Risk Assessment'!I6 -> 4.35 | D6: ='Risk Assessment'!J6 -> 87 | E6: =IF('Risk Assessment'!K6="","",'Risk Assessment'!K6) -> Yes | F6: =IF(D6="","",IF(E6="Yes","Tier 1",IF(D6>=75,"Tier 1",IF(D6>=45,"Tier 2","Tier 3")))) -> Tier 1 | H6: =IF(G6<>"",G6,F6) -> Tier 1 | I6: =IF(H6="","",IF(H6="Tier 1","Enhanced assessment + evidence validation",IF(H6="Tier 2","Standard security assessment","Basic screening"))) -> Enhanced assessment + evidence validation | J6: =IF(H6="","",IF(H6="Tier 1","Annual",IF(H6="Tier 2","Every 2 years","Every 3 years"))) -> Annual | K6: =IF('Vendor Inventory'!E6="","",'Vendor Inventory'!E6) -> Payroll Manager or HR Director | L6: Complete | M6: Tier 1 classification confirmed due to highly sensitive payroll, banking, tax, and employee data processed through automated integrations. Annual review should validate encryption, service-account controls, payroll continuity, and oversight of banking and tax-processing partners.
A7: V-003 | B7: =IF('Vendor Inventory'!B7="","",'Vendor Inventory'!B7) -> VenueBridge Tickets | C7: ='Risk Assessment'!I7 -> 4.35 | D7: ='Risk Assessment'!J7 -> 87 | E7: =IF('Risk Assessment'!K7="","",'Risk Assessment'!K7) -> Yes | F7: =IF(D7="","",IF(E7="Yes","Tier 1",IF(D7>=75,"Tier 1",IF(D7>=45,"Tier 2","Tier 3")))) -> Tier 1 | H7: =IF(G7<>"",G7,F7) -> Tier 1 | I7: =IF(H7="","",IF(H7="Tier 1","Enhanced assessment + evidence validation",IF(H7="Tier 2","Standard security assessment","Basic screening"))) -> Enhanced assessment + evidence validation | J7: =IF(H7="","",IF(H7="Tier 1","Annual",IF(H7="Tier 2","Every 2 years","Every 3 years"))) -> Annual | K7: =IF('Vendor Inventory'!E7="","",'Vendor Inventory'!E7) -> Director of Ticketing Operations | L7: In Progress | M7: Annual reassessment is underway before contract renewal. Tier 1 classification remains appropriate due to reliance on the platform for ticket sales, customer entry, revenue collection, and multiple system integrations. Updated resilience, incident-notification, and fourth-party evidence is pending.
A8: V-004 | B8: =IF('Vendor Inventory'!B8="","",'Vendor Inventory'!B8) -> Harrison, Cole & Mercer LLP | C8: ='Risk Assessment'!I8 -> 3.25 | D8: ='Risk Assessment'!J8 -> 65 | E8: =IF('Risk Assessment'!K8="","",'Risk Assessment'!K8) -> No | F8: =IF(D8="","",IF(E8="Yes","Tier 1",IF(D8>=75,"Tier 1",IF(D8>=45,"Tier 2","Tier 3")))) -> Tier 2 | H8: =IF(G8<>"",G8,F8) -> Tier 2 | I8: =IF(H8="","",IF(H8="Tier 1","Enhanced assessment + evidence validation",IF(H8="Tier 2","Standard security assessment","Basic screening"))) -> Standard security assessment | J8: =IF(H8="","",IF(H8="Tier 1","Annual",IF(H8="Tier 2","Every 2 years","Every 3 years"))) -> Every 2 years | K8: =IF('Vendor Inventory'!E8="","",'Vendor Inventory'!E8) -> General Counsel | L8: Complete | M8: Tier 2 classification confirmed. The firm handles highly confidential and legally privileged information but has limited user-level system access and lower availability requirements. Continue biennial review of secure document exchange, retention, least privilege, and subcontractor use.
A9: V-005 | B9: =IF('Vendor Inventory'!B9="","",'Vendor Inventory'!B9) -> Brightline Creative Group | C9: ='Risk Assessment'!I9 -> 2.55 | D9: ='Risk Assessment'!J9 -> 51 | E9: =IF('Risk Assessment'!K9="","",'Risk Assessment'!K9) -> No | F9: =IF(D9="","",IF(E9="Yes","Tier 1",IF(D9>=75,"Tier 1",IF(D9>=45,"Tier 2","Tier 3")))) -> Tier 2 | H9: =IF(G9<>"",G9,F9) -> Tier 2 | I9: =IF(H9="","",IF(H9="Tier 1","Enhanced assessment + evidence validation",IF(H9="Tier 2","Standard security assessment","Basic screening"))) -> Standard security assessment | J9: =IF(H9="","",IF(H9="Tier 1","Annual",IF(H9="Tier 2","Every 2 years","Every 3 years"))) -> Every 2 years | K9: =IF('Vendor Inventory'!E9="","",'Vendor Inventory'!E9) -> Marketing Director | L9: Complete | M9: Tier 2 classification confirmed due to customer marketing data, website and social-media access, and reliance on advertising and analytics partners. Review verified that individual accounts, MFA, access removal, and customer-data-sharing restrictions are required.
A10: V-006 | B10: =IF('Vendor Inventory'!B10="","",'Vendor Inventory'!B10) -> MetroDesk Office Supply | C10: ='Risk Assessment'!I10 -> 1.4 | D10: ='Risk Assessment'!J10 -> 28 | E10: =IF('Risk Assessment'!K10="","",'Risk Assessment'!K10) -> No | F10: =IF(D10="","",IF(E10="Yes","Tier 1",IF(D10>=75,"Tier 1",IF(D10>=45,"Tier 2","Tier 3")))) -> Tier 3 | H10: =IF(G10<>"",G10,F10) -> Tier 3 | I10: =IF(H10="","",IF(H10="Tier 1","Enhanced assessment + evidence validation",IF(H10="Tier 2","Standard security assessment","Basic screening"))) -> Basic screening | J10: =IF(H10="","",IF(H10="Tier 1","Annual",IF(H10="Tier 2","Every 2 years","Every 3 years"))) -> Every 3 years | K10: =IF('Vendor Inventory'!E10="","",'Vendor Inventory'!E10) -> Procurement Manager | L10: Complete | M10: Tier 3 classification confirmed. Vendor is easily replaceable, handles routine business information, and has no direct access to production systems. Basic screening and standard contractual protections are sufficient.
A11: V-007 | B11: =IF('Vendor Inventory'!B11="","",'Vendor Inventory'!B11) -> SentinelPeak Security | C11: ='Risk Assessment'!I11 -> 4.55 | D11: ='Risk Assessment'!J11 -> 91 | E11: =IF('Risk Assessment'!K11="","",'Risk Assessment'!K11) -> Yes | F11: =IF(D11="","",IF(E11="Yes","Tier 1",IF(D11>=75,"Tier 1",IF(D11>=45,"Tier 2","Tier 3")))) -> Tier 1 | H11: =IF(G11<>"",G11,F11) -> Tier 1 | I11: =IF(H11="","",IF(H11="Tier 1","Enhanced assessment + evidence validation",IF(H11="Tier 2","Standard security assessment","Basic screening"))) -> Enhanced assessment + evidence validation | J11: =IF(H11="","",IF(H11="Tier 1","Annual",IF(H11="Tier 2","Every 2 years","Every 3 years"))) -> Annual | K11: =IF('Vendor Inventory'!E11="","",'Vendor Inventory'!E11) -> Chief Information Security Officer | L11: In Progress | M11: Tier 1 onboarding assessment is in progress. Privileged access must not be activated until MFA, PAM controls, access logging, incident-response procedures, personnel screening, and business-continuity evidence are validated.
A12: V-008 | B12: =IF('Vendor Inventory'!B12="","",'Vendor Inventory'!B12) -> CrowdFlow Access Systems | C12: ='Risk Assessment'!I12 -> 4.45 | D12: ='Risk Assessment'!J12 -> 89 | E12: =IF('Risk Assessment'!K12="","",'Risk Assessment'!K12) -> Yes | F12: =IF(D12="","",IF(E12="Yes","Tier 1",IF(D12>=75,"Tier 1",IF(D12>=45,"Tier 2","Tier 3")))) -> Tier 1 | H12: =IF(G12<>"",G12,F12) -> Tier 1 | I12: =IF(H12="","",IF(H12="Tier 1","Enhanced assessment + evidence validation",IF(H12="Tier 2","Standard security assessment","Basic screening"))) -> Enhanced assessment + evidence validation | J12: =IF(H12="","",IF(H12="Tier 1","Annual",IF(H12="Tier 2","Every 2 years","Every 3 years"))) -> Annual | K12: =IF('Vendor Inventory'!E12="","",'Vendor Inventory'!E12) -> Venue Operations Manager | L12: Needs Escalation | M12: Tier 1 renewal requires management escalation due to mission-critical venue access, privileged connectivity, high availability requirements, and reliance on a Russia-based fourth party. Legal and Compliance must complete sanctions, ownership, banking, and export-control reviews before renewal approval.
A13: V-009 | B13: =IF('Vendor Inventory'!B13="","",'Vendor Inventory'!B13) -> HarborPoint Payment Solutions | C13: ='Risk Assessment'!I13 -> 4.8 | D13: ='Risk Assessment'!J13 -> 96 | E13: =IF('Risk Assessment'!K13="","",'Risk Assessment'!K13) -> Yes | F13: =IF(D13="","",IF(E13="Yes","Tier 1",IF(D13>=75,"Tier 1",IF(D13>=45,"Tier 2","Tier 3")))) -> Tier 1 | H13: =IF(G13<>"",G13,F13) -> Tier 1 | I13: =IF(H13="","",IF(H13="Tier 1","Enhanced assessment + evidence validation",IF(H13="Tier 2","Standard security assessment","Basic screening"))) -> Enhanced assessment + evidence validation | J13: =IF(H13="","",IF(H13="Tier 1","Annual",IF(H13="Tier 2","Every 2 years","Every 3 years"))) -> Annual | K13: =IF('Vendor Inventory'!E13="","",'Vendor Inventory'!E13) -> Finance Director or Controller | L13: Needs Escalation | M13: Tier 1 vendor remains in remediation due to payment-card exposure, critical revenue dependency, API integrations, and extensive financial fourth parties. Renewal requires current PCI DSS evidence, stronger incident-notification terms, and validated closure of payment-security findings.
A14: V-010 | B14: =IF('Vendor Inventory'!B14="","",'Vendor Inventory'!B14) -> StageLink Production Services | C14: ='Risk Assessment'!I14 -> 3.1 | D14: ='Risk Assessment'!J14 -> 62 | E14: =IF('Risk Assessment'!K14="","",'Risk Assessment'!K14) -> No | F14: =IF(D14="","",IF(E14="Yes","Tier 1",IF(D14>=75,"Tier 1",IF(D14>=45,"Tier 2","Tier 3")))) -> Tier 2 | H14: =IF(G14<>"",G14,F14) -> Tier 2 | I14: =IF(H14="","",IF(H14="Tier 1","Enhanced assessment + evidence validation",IF(H14="Tier 2","Standard security assessment","Basic screening"))) -> Standard security assessment | J14: =IF(H14="","",IF(H14="Tier 1","Annual",IF(H14="Tier 2","Every 2 years","Every 3 years"))) -> Every 2 years | K14: =IF('Vendor Inventory'!E14="","",'Vendor Inventory'!E14) -> Director of Event Production | L14: Complete | M14: Tier 2 classification confirmed. Production services are important during live events, but the vendor handles limited sensitive data. Network-connected production equipment must remain isolated, temporary access must be approved, and accounts and devices must be removed after events.
A15: V-011 | B15: =IF('Vendor Inventory'!B15="","",'Vendor Inventory'!B15) -> IronGate Facility Management | C15: ='Risk Assessment'!I15 -> 3.25 | D15: ='Risk Assessment'!J15 -> 65 | E15: =IF('Risk Assessment'!K15="","",'Risk Assessment'!K15) -> No | F15: =IF(D15="","",IF(E15="Yes","Tier 1",IF(D15>=75,"Tier 1",IF(D15>=45,"Tier 2","Tier 3")))) -> Tier 2 | H15: =IF(G15<>"",G15,F15) -> Tier 2 | I15: =IF(H15="","",IF(H15="Tier 1","Enhanced assessment + evidence validation",IF(H15="Tier 2","Standard security assessment","Basic screening"))) -> Standard security assessment | J15: =IF(H15="","",IF(H15="Tier 1","Annual",IF(H15="Tier 2","Every 2 years","Every 3 years"))) -> Every 2 years | K15: =IF('Vendor Inventory'!E15="","",'Vendor Inventory'!E15) -> Facilities Manager | L15: Complete | M15: Tier 2 classification confirmed due to physical access, operational importance, and reliance on specialty contractors. Continue biennial review of restricted-area access, escort requirements, safety compliance, and subcontractor approval.
A16: V-012 | B16: =IF('Vendor Inventory'!B16="","",'Vendor Inventory'!B16) -> SafeGuard Event Staffing | C16: ='Risk Assessment'!I16 -> 3.95 | D16: ='Risk Assessment'!J16 -> 79 | E16: =IF('Risk Assessment'!K16="","",'Risk Assessment'!K16) -> Yes | F16: =IF(D16="","",IF(E16="Yes","Tier 1",IF(D16>=75,"Tier 1",IF(D16>=45,"Tier 2","Tier 3")))) -> Tier 1 | H16: =IF(G16<>"",G16,F16) -> Tier 1 | I16: =IF(H16="","",IF(H16="Tier 1","Enhanced assessment + evidence validation",IF(H16="Tier 2","Standard security assessment","Basic screening"))) -> Enhanced assessment + evidence validation | J16: =IF(H16="","",IF(H16="Tier 1","Annual",IF(H16="Tier 2","Every 2 years","Every 3 years"))) -> Annual | K16: =IF('Vendor Inventory'!E16="","",'Vendor Inventory'!E16) -> Director of Venue Security | L16: Complete | M16: Tier 1 classification confirmed because event security and crowd management are essential to attendee safety and venue operations. Annual review must validate guard licensing, background checks, staffing continuity, incident-reporting procedures, and approval of subcontracted guards.
... A19: V-015 | B19: =IF('Vendor Inventory'!B19="","",'Vendor Inventory'!B19) -> EverSafe Insurance Partners | C19: ='Risk Assessment'!I19 -> 3.45 | D19: ='Risk Assessment'!J19 -> 69 | E19: =IF('Risk Assessment'!K19="","",'Risk Assessment'!K19) -> No | F19: =IF(D19="","",IF(E19="Yes","Tier 1",IF(D19>=75,"Tier 1",IF(D19>=45,"Tier 2","Tier 3")))) -> Tier 2 | H19: =IF(G19<>"",G19,F19) -> Tier 2 | I19: =IF(H19="","",IF(H19="Tier 1","Enhanced assessment + evidence validation",IF(H19="Tier 2","Standard security assessment","Basic screening"))) -> Standard security assessment | J19: =IF(H19="","",IF(H19="Tier 1","Annual",IF(H19="Tier 2","Every 2 years","Every 3 years"))) -> Every 2 years | K19: =IF('Vendor Inventory'!E19="","",'Vendor Inventory'!E19) -> Chief Financial Officer or Risk Manager | L19: Complete | M19: Tier 2 classification confirmed despite highly sensitive claims information because system access and real-time availability requirements are limited. Continue biennial review of secure file transfer, retention, confidentiality, claims subprocessors, adjusters, and reinsurers.
A20: V-016 | B20: =IF('Vendor Inventory'!B20="","",'Vendor Inventory'!B20) -> DataPulse Analytics | C20: ='Risk Assessment'!I20 -> 3.55 | D20: ='Risk Assessment'!J20 -> 71 | E20: =IF('Risk Assessment'!K20="","",'Risk Assessment'!K20) -> No | F20: =IF(D20="","",IF(E20="Yes","Tier 1",IF(D20>=75,"Tier 1",IF(D20>=45,"Tier 2","Tier 3")))) -> Tier 2 | G20: Tier 1 | H20: =IF(G20<>"",G20,F20) -> Tier 1 | I20: =IF(H20="","",IF(H20="Tier 1","Enhanced assessment + evidence validation",IF(H20="Tier 2","Standard security assessment","Basic screening"))) -> Enhanced assessment + evidence validation | J20: =IF(H20="","",IF(H20="Tier 1","Annual",IF(H20="Tier 2","Every 2 years","Every 3 years"))) -> Annual | K20: =IF('Vendor Inventory'!E20="","",'Vendor Inventory'!E20) -> Marketing Analytics Manager | L20: Needs Escalation | M20: Temporarily elevated from Tier 2 to Tier 1 due to active remediation, broad API and service-account access, large-scale customer profiling, and extensive ticketing and behavioral data processing. Return to Tier 2 only after remediation evidence is validated, access is restricted, data-minimization and retention controls are confirmed, and residual risk is formally approved.
A21: V-017 | B21: =IF('Vendor Inventory'!B21="","",'Vendor Inventory'!B21) | C21: ='Risk Assessment'!I21 | D21: ='Risk Assessment'!J21 | E21: =IF('Risk Assessment'!K21="","",'Risk Assessment'!K21) | F21: =IF(D21="","",IF(E21="Yes","Tier 1",IF(D21>=75,"Tier 1",IF(D21>=45,"Tier 2","Tier 3")))) | H21: =IF(G21<>"",G21,F21) | I21: =IF(H21="","",IF(H21="Tier 1","Enhanced assessment + evidence validation",IF(H21="Tier 2","Standard security assessment","Basic screening"))) | J21: =IF(H21="","",IF(H21="Tier 1","Annual",IF(H21="Tier 2","Every 2 years","Every 3 years"))) | K21: =IF('Vendor Inventory'!D21="","",'Vendor Inventory'!D21)
A22: V-018 | B22: =IF('Vendor Inventory'!B22="","",'Vendor Inventory'!B22) | C22: ='Risk Assessment'!I22 | D22: ='Risk Assessment'!J22 | E22: =IF('Risk Assessment'!K22="","",'Risk Assessment'!K22) | F22: =IF(D22="","",IF(E22="Yes","Tier 1",IF(D22>=75,"Tier 1",IF(D22>=45,"Tier 2","Tier 3")))) | H22: =IF(G22<>"",G22,F22) | I22: =IF(H22="","",IF(H22="Tier 1","Enhanced assessment + evidence validation",IF(H22="Tier 2","Standard security assessment","Basic screening"))) | J22: =IF(H22="","",IF(H22="Tier 1","Annual",IF(H22="Tier 2","Every 2 years","Every 3 years"))) | K22: =IF('Vendor Inventory'!D22="","",'Vendor Inventory'!D22)
A23: V-019 | B23: =IF('Vendor Inventory'!B23="","",'Vendor Inventory'!B23) | C23: ='Risk Assessment'!I23 | D23: ='Risk Assessment'!J23 | E23: =IF('Risk Assessment'!K23="","",'Risk Assessment'!K23) | F23: =IF(D23="","",IF(E23="Yes","Tier 1",IF(D23>=75,"Tier 1",IF(D23>=45,"Tier 2","Tier 3")))) | H23: =IF(G23<>"",G23,F23) | I23: =IF(H23="","",IF(H23="Tier 1","Enhanced assessment + evidence validation",IF(H23="Tier 2","Standard security assessment","Basic screening"))) | J23: =IF(H23="","",IF(H23="Tier 1","Annual",IF(H23="Tier 2","Every 2 years","Every 3 years"))) | K23: =IF('Vendor Inventory'!D23="","",'Vendor Inventory'!D23)
A24: V-020 | B24: =IF('Vendor Inventory'!B24="","",'Vendor Inventory'!B24) | C24: ='Risk Assessment'!I24 | D24: ='Risk Assessment'!J24 | E24: =IF('Risk Assessment'!K24="","",'Risk Assessment'!K24) | F24: =IF(D24="","",IF(E24="Yes","Tier 1",IF(D24>=75,"Tier 1",IF(D24>=45,"Tier 2","Tier 3")))) | H24: =IF(G24<>"",G24,F24) | I24: =IF(H24="","",IF(H24="Tier 1","Enhanced assessment + evidence validation",IF(H24="Tier 2","Standard security assessment","Basic screening"))) | J24: =IF(H24="","",IF(H24="Tier 1","Annual",IF(H24="Tier 2","Every 2 years","Every 3 years"))) | K24: =IF('Vendor Inventory'!D24="","",'Vendor Inventory'!D24)

Sheet Dashboard
A1: TPRM Tiering Dashboard
A3: A high-level view of the vendor population and inherent-risk profile.
A5: KPI | B5: Value | D5: Risk Indicator | E5: Count
A6: Total Vendors | B6: =COUNTIF('Vendor Inventory'!B5:B24,"<>") -> 16 | D6: Unassessed Vendors | E6: =COUNTIF('Risk Assessment'!J5:J24,"")-COUNTIF('Vendor Inventory'!B5:B24,"") -> 0
A7: Tier 1 | B7: =COUNTIF('Tiering Results'!H5:H24,"Tier 1") -> 8 | D7: Auto Tier 1 Triggers | E7: =COUNTIF('Risk Assessment'!K5:K24,"Yes") -> 7
A8: Tier 2 | B8: =COUNTIF('Tiering Results'!H5:H24,"Tier 2") -> 7 | D8: High Data Sensitivity (5) | E8: =COUNTIF('Risk Assessment'!D5:D24,5) -> 5
A9: Tier 3 | B9: =COUNTIF('Tiering Results'!H5:H24,"Tier 3") -> 1 | D9: Privileged / High Access (4–5) | E9: =COUNTIF('Risk Assessment'!E5:E24,">=4") -> 7
D10: Critical Availability (5) | E10: =COUNTIF('Risk Assessment'!H5:H24,5) -> 6
A12: Tier | B12: Vendor Count
A13: Tier 1 | B13: =B7 -> 8
A14: Tier 2 | B14: =B8 -> 7
A15: Tier 3 | B15: =B9 -> 1
A18: Risk Band | B18: Definition
A19: Tier 1 | B19: Highest inherent risk; deepest assessment and monitoring.
A20: Tier 2 | B20: Moderate inherent risk; standard assessment and evidence review.
A21: Tier 3 | B21: Lower inherent risk; basic screening and standard controls.
A23: Interpretation | B23: The score identifies assessment depth. It does not prove the vendor is secure.
A24: Reminder | B24: Residual risk is evaluated after reviewing controls and evidence.

Sheet Executive Summary
A1: Vendor Inventory & Risk-Tiering Project
A3: Purpose: identify which third parties require the deepest due diligence, monitoring, and executive attention.
A5: Portfolio Overview
A6: Metric | B6: Result | D6: Executive Narrative
A7: Total vendors entered | B7: =COUNTIF('Vendor Inventory'!B5:B24,"<>") -> 16 | D7: WallGate Events & Entertainment maintains an inventory of 16 third-party vendors supporting cloud hosting, payroll, ticketing, cybersecurity, payment processing, venue access, event staffing, facilities, marketing, and other business functions. The inherent-risk assessment classified eight vendors as Tier 1, seven as Tier 2, and one as Tier 3. The highest risks are concentrated among vendors with privileged or automated system access, sensitive personal or payment data, high availability requirements, and substantial fourth-party dependencies. Immediate management attention is required for CrowdFlow Access Systems, HarborPoint Payment Solutions, and DataPulse Analytics due to geopolitical exposure, active remediation, and elevated data-access risks. WallGate should complete enhanced assessments, validate remediation evidence, strengthen contractual protections, and prevent production access until onboarding and due-diligence requirements are satisfied.
A8: Tier 1 vendors | B8: =COUNTIF('Tiering Results'!H5:H24,"Tier 1") -> 8
A9: Tier 2 vendors | B9: =COUNTIF('Tiering Results'!H5:H24,"Tier 2") -> 7
A10: Tier 3 vendors | B10: =COUNTIF('Tiering Results'!H5:H24,"Tier 3") -> 1
A12: Key Risk Themes
A13: Theme | B13: Observation / Evidence | C13: Affected Vendors | D13: Management Impact | E13: Recommended Action | F13: Owner | G13: Target Date | H13: Status
A14: Tier 1 concentration | B14: Eight of 16 vendors were classified as Tier 1 because of critical services, sensitive data, privileged access, regulatory exposure, or high availability requirements. | C14: V-001, V-002, V-003, V-007, V-008, V-009, V-012, V-016 | D14: Failure or compromise could disrupt events, payroll, payments, cybersecurity monitoring, customer entry, or sensitive-data protection. | E14: Complete enhanced assessments and validate security, resilience, access-control, incident-response, and fourth-party evidence annually. | F14: GRC/TPRM Analyst and Business Owners | G14: 46295 | H14: In Progress
A15: Geopolitical and sanctions exposure | B15: CrowdFlow relies on a fictional Russia-based development and support subcontractor with potential privileged access and operational dependency. | C15: V-008 | D15: Sanctions, banking restrictions, export controls, or loss of support could interrupt venue-access services and delay renewal. | E15: Require sanctions and ownership screening, banking review, access validation, conditional renewal, and a geographic exit plan. | F15: Legal, Compliance, Security, and Procurement | G15: 46265 | H15: Needs Escalation
A16: Unresolved remediation | B16: HarborPoint and DataPulse have open findings involving payment security, API access, customer profiling, retention, and downstream data sharing. | C16: V-009, V-016 | D16: Unresolved weaknesses could lead to payment disruption, privacy incidents, regulatory exposure, or unacceptable residual risk. | E16: Validate corrective-action evidence, assign accountable owners, track deadlines, and escalate overdue findings before renewal approval. | F16: GRC, Security, Finance, and Marketing | G16: 46356 | H16: Needs Escalation
A17: Incomplete onboarding and pre-contract review | B17: SentinelPeak and FreshTable are onboarding, while RapidRoute remains planned. Assessments are not yet fully completed. | C17: V-007, V-013, V-014 | D17: Premature access or data sharing could expose WallGate before security, privacy, insurance, and contractual controls are verified. | E17: Prevent production access and personal-data sharing until due diligence, contract review, and required evidence are approved. | F17: Procurement, GRC, and Business Owners | G17: 46265 | H17: In Progress
A19: Management Recommendations
A20: 1. Complete enhanced due diligence for all eight Tier 1 vendors, including validation of security certifications, penetration tests, access controls, incident-response plans, business-continuity testing, and fourth-party oversight. 2. Grant CrowdFlow Access Systems only a conditional short-term renewal until sanctions screening, ownership validation, privileged-access review, and the geographic exit plan are completed. 3. Require HarborPoint Payment Solutions and DataPulse Analytics to submit documented remediation evidence before long-term renewal or residual-risk acceptance. 4. Prohibit production access and sensitive-data sharing for SentinelPeak Security, FreshTable Hospitality Group, and RapidRoute Transportation until onboarding and due diligence are approved. 5. Maintain a centralized reassessment calendar requiring annual reviews for Tier 1 vendors, reviews every two years for Tier 2 vendors, and reviews every three years for Tier 3 vendors, with additional reviews triggered by incidents, ownership changes, sanctions exposure, or significant service changes.
